mesh_generator/__init__.py
mesh_generator/bin/__init__.py
mesh_generator/bin/call_mesh_shell_command.py
mesh_generator/bin/call_psi_mesh_tool.py
mesh_generator/bin/mesh_header_template.py
mesh_generator/bin/plot_legacy_mesh.py
mesh_generator/bin/plot_mesh_res_file.py
mesh_generator/bin/plot_seg.py
mesh_generator/bin/psi_mesh_tool.py
mesh_generator/bin/shell_command.py
mesh_generator/bin/tmp_mas_template.py
mesh_generator/hdf/__init__.py
mesh_generator/hdf/psihdf.py
mesh_generator/hdf/read_mesh_res.py
mesh_generator/hdf/write_1d_hdf_files.py
mesh_generator/src/__init__.py
mesh_generator/src/legacy_mesh.py
mesh_generator/src/legacy_mesh_segment.py
mesh_generator/src/mesh.py
mesh_generator/src/mesh_optimizer.py
mesh_generator/src/mesh_segment.py
mesh_generator/ui/__init__.py
mesh_generator/ui/auto_mesh_from_dict.py
mesh_generator/ui/mesh_box.py
mesh_generator/ui/mesh_info.py
mesh_generator/ui/mesh_num_points.py
mesh_generator/ui/my_axes.py
mesh_generator/ui/psihdf.py
mesh_generator/ui/read_hdf.py
mesh_generator/ui/restrictor_pan.py
mesh_generator/ui/save_dict.py
mesh_generator/ui/scroll_bar.py
mesh_generator/ui/table_chart.py
mesh_generator/ui/test_pcolorfast.py
mesh_generator/ui/tkinter_mainapp.py
mesh_generator/ui/upload_magnetogram.py
mesh_generator-1.1.11.dist-info/licenses/LICENSE
mesh_generator-1.1.11.dist-info/METADATA
mesh_generator-1.1.11.dist-info/WHEEL
mesh_generator-1.1.11.dist-info/top_level.txt
mesh_generator-1.1.11.dist-info/RECORD
