Metadata-Version: 2.4
Name: mesh_generator
Version: 1.1.11
Summary: Python subroutines to create a 1D mesh in Python.
Home-page: https://bitbucket.org/predsci/mesh_generator
Author: Predictive Science Inc
Author-email: oissan@predsci.com
Keywords: Mesh Generation,Grid
Classifier: Programming Language :: Python :: 3
Classifier: Operating System :: OS Independent
Classifier: Topic :: Scientific/Engineering :: Astronomy
Classifier: Topic :: Scientific/Engineering :: Mathematics
Requires-Python: >=3.5
License-File: LICENSE
Requires-Dist: numpy>=1.15.2
Requires-Dist: matplotlib>=3.0.0
Requires-Dist: scipy>=1.1.0
Requires-Dist: pyhdf>=0.9.10
Requires-Dist: h5py>=2.8.0
Dynamic: author
Dynamic: author-email
Dynamic: classifier
Dynamic: description
Dynamic: description-content-type
Dynamic: home-page
Dynamic: keywords
Dynamic: license-file
Dynamic: requires-dist
Dynamic: requires-python
Dynamic: summary
